{
    "context": {
        "domain": "rental",
        "action": "on_init",
        "version": "1.1.0",
        "bap_id": "bap-ps-network-dev.becknprotocol.io",
        "bpp_id": "bpp-ps-network-strapi2-dev.becknprotocol.io",
        "bpp_uri": "http://bpp-ps-network-strapi2-dev.becknprotocol.io",
        "transaction_id": "924dd6fb-8896-476e-9918-b0faf06d3e77",
        "message_id": "on_init-message-001",
        "timestamp": "2025-04-15T15:51:01.000Z",
        "location": {
            "country": {
                "code": "USA"
            },
            "city": {
                "code": "NANP:628"
            }
        }
    },
    "message": {
        "order": {
            "provider": {
                "id": "299",
                "descriptor": {
                    "name": "San Francisco Energy Depot",
                    "short_desc": "Battery",
                    "long_desc": "Battery",
                    "images": [
                        {
                            "url": "https://m.media-amazon.com/images/I/51D9ZUF9W-L._AC_SX679_.jpg",
                            "size_type": "sm"
                        }
                    ]
                }
            },
            "items": [
                {
                    "id": "420",
                    "descriptor": {
                        "name": "STARMAX GC STCR-305 – 6-Volt Deep Cycle Flooded Battery",
                        "short_desc": "305Ah X 8"
                    },
                    "price": {
                        "value": "10",
                        "currency": "USD"
                    },
                    "quantity": {
                        "selected": {
                            "count": 1
                        },
                        "available": {
                            "count": 1000
                        }
                    }
                }
            ],
            "fulfillments": [
                {
                    "id": "569",
                    "type": "HOME_DELIVERY",
                    "stops": [
                        {
                            "type": "start",
                            "location": {
                                "address": "Warehouse 21, SF Industrial Area"
                            },
                            "time": {
                                "range": {
                                    "start": "2025-04-16T09:00:00Z",
                                    "end": "2025-04-16T10:00:00Z"
                                }
                            }
                        },
                        {
                            "type": "end",
                            "location": {
                                "address": "123 Battery Street, San Francisco, CA"
                            },
                            "time": {
                                "range": {
                                    "start": "2025-04-16T10:30:00Z",
                                    "end": "2025-04-16T11:30:00Z"
                                }
                            }
                        }
                    ]
                }
            ],
            "billing": {
                "name": "Jane Doe",
                "phone": "+14155552671",
                "email": "jane.doe@example.com",
                "address": "123 Battery Street, San Francisco, CA"
            },
            "quote": {
                "price": {
                    "currency": "USD",
                    "value": "10.00"
                },
                "breakup": [
                    {
                        "title": "Battery Rental",
                        "price": {
                            "value": "10.00",
                            "currency": "USD"
                        }
                    }
                ]
            },
            "payments": [
                {
                    "type": "ON-FULFILLMENT",
                    "collected_by": "BPP",
                    "params": {
                        "amount": "10.00",
                        "currency": "USD"
                    }
                }
            ],
            "return_terms": [
                {
                    "fulfillment_state": {
                            "code": "delivered",
                            "name": "Delivered"
                    },
                    "return_eligible": true,
                    "return_time": {
                        "timestamp": "2025-05-14T23:59:59Z"
                    },
                    "return_location": {
                        "id": "return-loc-001",
                        "descriptor": {
                            "name": "Return Center"
                        },
                        "gps": "37.7749,-122.4194",
                        "address": "Warehouse 5, Bay Area, CA"
                    },
                    "fulfillment_managed_by": "CONSUMER"
                }
            ],
            "cancellation_terms": [
                {
                    "fulfillment_state": {
                        "descriptor": {
                            "code": "order_placed",
                            "name": "Order Placed"
                        }
                    },
                    "reason_required": true,
                    "cancel_by": {
                        "timestamp": "2025-05-07T20:00:00Z"
                    },
                    "cancellation_fee": {
                        "percentage": 5,
                        "minimum_value": {
                            "currency": "USD",
                            "value": "10"
                        }
                    },
                    "xinput": {
                        "required": true,
                        "form": {
                            "url": "https://example.com/cancel"
                        }
                    },
                    "external_ref": {
                        "url": "https://example.com/docs/cancellation-policy.pdf",
                        "mime_type": "application/pdf"
                    }
                }
            ]
        }
    }
}